Metadata-Version: 1.0
Name: swimbundle-dev
Version: 0.1.2
Summary: Swimlane Bundle Development Package
Home-page: UNKNOWN
Author: Swimlane
Author-email: info@swimlane.com
License: UNKNOWN
Keywords: dev,development
Platform: UNKNOWN
